e2e.api-0.1.2-py3.6-nspkg.pth
e2e/__init__.pyi
e2e/api/__init__.py
e2e/api/api.py
e2e/api/base.py
e2e/api/decorators.py
e2e/api/endpoint.py
e2e/api/exceptions.py
e2e/api/py.typed
e2e/api/types.py
e2e.api-0.1.2.dist-info/LICENSE
e2e.api-0.1.2.dist-info/METADATA
e2e.api-0.1.2.dist-info/WHEEL
e2e.api-0.1.2.dist-info/namespace_packages.txt
e2e.api-0.1.2.dist-info/top_level.txt
e2e.api-0.1.2.dist-info/RECORD
